itk/ANTsWasmPython.py
itk/Configuration/ANTsWasmConfig.py
itk/Configuration/ANTsWasm_snake_case.py
itk/_ANTsWasmPython.so
itk/itkANTSGroupwiseBuildTemplatePython.py
itk/itkANTSRegistrationPython.py
itk_ants-0.8.1.dist-info/METADATA
itk_ants-0.8.1.dist-info/WHEEL
itk_ants-0.8.1.dist-info/entry_points.txt
itk_ants-0.8.1.dist-info/licenses/LICENSE
itk_ants-0.8.1.dist-info/RECORD
