Metadata-Version: 2.1
Name: itk-ants
Version: 0.8.1
Summary: Advanced Normalization Tools in WebAssembly
Keywords: itk,ants
Author-Email: "Matthew M. McCormick" <matt.mccormick@kitware.com>, =?utf-8?b?RMW+ZW5hbiBadWtpxIc=?= <dzenan.zukic@kitware.com>
License:                                  Apache License
Classifier: Development Status :: 4 - Beta
Classifier: Intended Audience :: Developers
Classifier: Intended Audience :: Education
Classifier: Intended Audience :: Healthcare Industry
Classifier: Intended Audience :: Science/Research
Classifier: License :: OSI Approved :: Apache Software License
Classifier: Operating System :: Android
Classifier: Operating System :: MacOS
Classifier: Operating System :: Microsoft :: Windows
Classifier: Operating System :: POSIX
Classifier: Operating System :: Unix
Classifier: Programming Language :: C++
Classifier: Programming Language :: Python
Classifier: Topic :: Scientific/Engineering
Classifier: Topic :: Scientific/Engineering :: Information Analysis
Classifier: Topic :: Scientific/Engineering :: Medical Science Apps.
Classifier: Topic :: Software Development :: Libraries
Project-URL: Download, https://github.com/thewtex/ANTsWasm
Project-URL: Homepage, https://github.com/thewtex/ANTsWasm
Requires-Python: >=3.8
Requires-Dist: itk==5.4.*
License-File: LICENSE
